{
    "azure": {
        "tenantId": "9f49ae42-72e9-429b-bab6-4ef9324a672e",
        "subscriptionId": "8d223c38-245a-49eb-b46d-d238063b4dab",
        "resourceGroup": "securityresources-rg",
        "workspaceName": "test-sentinel"
    },
    "analysis": {
        "stalenessThresholds": {
            "warning": 3,
            "critical": 7
        },
        "excludedTables": [],
        "excludedRules": []
    },
    "visualization": {
        "networkGraph": {
            "enabled": true,
            "format": "svg",
            "nodeColorScheme": {
                "active": "#4CAF50",
                "warning": "#FFC107",
                "critical": "#F44336",
                "rule": "#2196F3"
            }
        },
        "heatmap": {
            "enabled": true,
            "colorScheme": "RdYlGn"
        },
        "powerBI": {
            "enabled": true,
            "templatePath": "templates/CoverageAnalysis.pbit"
        }
    },
    "reporting": {
        "formats": ["csv", "html", "excel"],
        "outputPath": "output",
        "includeTimestamp": true
    },
    "logging": {
        "level": "Information",
        "path": "logs/coverage-analyzer.log"
    }
} 